studatio/cal_handler.py
studatio/cfg.py
studatio/events.py
studatio/main.py
studatio/storage.py
studatio/user_config.py
studatio-1.3.2.dist-info/METADATA
studatio-1.3.2.dist-info/entry_points.txt
studatio-1.3.2.dist-info/WHEEL
studatio-1.3.2.dist-info/LICENSE.txt
studatio-1.3.2.dist-info/RECORD
