Metadata-Version: 2.1
Name: studatio
Version: 1.3.2
Summary: Personal tool for my violin teaching database
Home-page: https://github.com/elizaaverywilson/studatio
License: MIT
Author: Eliza Wilson
Author-email: elizaaverywilson@gmail.com
Requires-Python: >=3.9,<3.11
Classifier: License :: OSI Approved :: MIT License
Classifier: Programming Language :: Python :: 3
Classifier: Programming Language :: Python :: 3.9
Classifier: Programming Language :: Python :: 3.10
Requires-Dist: appdirs (>=1.4.4,<2.0.0)
Requires-Dist: click (>=8.1.3,<9.0.0)
Requires-Dist: icalevents (>=0.1.27,<0.2.0)
Requires-Dist: pyperclip (>=1.8.2,<2.0.0)
Requires-Dist: tomlkit (>=0.11.4,<0.12.0)
Project-URL: Repository, https://github.com/elizaaverywilson/studatio
